s3peat/__init__.py
s3peat/scripts.py
s3peat-2.0.0.dist-info/METADATA
s3peat-2.0.0.dist-info/WHEEL
s3peat-2.0.0.dist-info/entry_points.txt
s3peat-2.0.0.dist-info/licenses/LICENSE.md
s3peat-2.0.0.dist-info/RECORD
