Metadata-Version: 2.4
Name: s3peat
Version: 2.0.0
Summary: Fast uploader to S3
Project-URL: Homepage, http://github.com/shakefu/s3peat
Project-URL: Repository, http://github.com/shakefu/s3peat
Project-URL: Issues, http://github.com/shakefu/s3peat/issues
Author-email: Jacob Alheid <shakefu@gmail.com>
License-Expression: MIT
License-File: LICENSE.md
Classifier: Development Status :: 5 - Production/Stable
Classifier: Intended Audience :: Developers
Classifier: License :: OSI Approved :: MIT License
Classifier: Operating System :: OS Independent
Classifier: Programming Language :: Python :: 3
Classifier: Programming Language :: Python :: 3.8
Classifier: Programming Language :: Python :: 3.9
Classifier: Programming Language :: Python :: 3.10
Classifier: Programming Language :: Python :: 3.11
Classifier: Programming Language :: Python :: 3.12
Requires-Python: >=3.8
Requires-Dist: boto3>=1.26.0
Requires-Dist: pytool>=4.0.0
